autocompose.py
setup.py
docker_autocompose.egg-info/PKG-INFO
docker_autocompose.egg-info/SOURCES.txt
docker_autocompose.egg-info/dependency_links.txt
docker_autocompose.egg-info/entry_points.txt
docker_autocompose.egg-info/requires.txt
docker_autocompose.egg-info/top_level.txt