Metadata-Version: 1.0
Name: docker-autocompose
Version: 1.0.1
Summary: Generate a docker-compose yaml definition from a running container
Home-page: https://github.com/Red5d/docker-autocompose
Author: Red5d
Author-email: UNKNOWN
License: GPLv2
Keywords: docker yaml container
Platform: UNKNOWN
